__init__.py
mcp_adapter/__init__.py
mcp_adapter/core/__init__.py
mcp_adapter/core/mcp_server_manager.py
mcp_adapter/core/schema.py
mcp_adapter/core/server_base.py
mcp_adapter-0.0.3.dist-info/METADATA
mcp_adapter-0.0.3.dist-info/WHEEL
mcp_adapter-0.0.3.dist-info/top_level.txt
mcp_adapter-0.0.3.dist-info/RECORD
