Metadata-Version: 2.4
Name: mcp-adapter
Version: 0.0.3
Summary: 基于FastAPI，以类集成的方式快速实现mcp tools以及服务挂载
Author-email: Jinsong Li <manson.li3307@gmail.com>
Requires-Python: >=3.10
Requires-Dist: fastapi
Requires-Dist: mcp
Requires-Dist: docstring_parser
Requires-Dist: pydantic
